{"paths":{"0":["res/sounds/nhac_nen",3],"1":["res/game/bg_2",0],"2":["res/game/bg_chat",0],"3":["res/game/round_1",0],"4":["res/game/button_huy",0],"5":["res/game/button_datcuoc",0],"6":["res/popup/choi_ngay/round_1",0],"7":["res/popup/history/round_1",0],"8":["res/game/bg_Gold",0],"9":["res/game/round_chat",0],"10":["res/common/iconCoinFish",0],"11":["res/game/tag_inactive",0],"12":["res/game/bg_top",0],"13":["res/game/icAdd",0],"14":["res/game/mien_trung_inactive",0],"15":["res/game/bg_1",0],"16":["res/game/Arrow",0],"17":["res/game/bg",0],"18":["res/game/lich_su_cuoc",0],"19":["res/game/mien_bac_inactive",0],"20":["res/game/mien_nam_inactive",0],"21":["res/popup/choi_ngay/bg_2",0],"22":["res/game/bg_4",0],"23":["res/popup/textTitleHis",0],"24":["res/game/round_cuoc",0],"25":["res/game/so_chua_chon",0],"26":["res/game/icon_back",0],"27":["res/game/round_date_location",0],"28":["res/popup/history/round 2",0],"29":["res/popup/textTitleResult",0],"30":["res/game/button_gui",0],"31":["res/game/round_2_active",0],"32":["res/game/so_da_chon_1",0],"33":["res/game/ket_qua_hang_ngay",0],"34":["res/game/so_da_chon",0],"35":["res/game/button_an_hien",0],"36":["res/game/tag_active",0],"37":["res/game/round_2_inactive",0],"38":["res/game/button_huy",1,1],"39":["res/game/mien_bac_inactive",1,1],"40":["res/game/round_2_active",1,1],"41":["res/game/tag_inactive",1,1],"42":["res/game/icAdd",1,1],"44":["res/game/round_cuoc",1,1],"45":["res/game/round_1",1,1],"46":["res/prefabs/Loto/Loto_ItemHistory",2],"47":["res/game/button_gui",1,1],"48":["res/popup/textTitleHis",1,1],"49":["res/game/so_chua_chon",1,1],"50":["res/game/round_2_inactive",1,1],"51":["res/game/Arrow",1,1],"52":["res/game/tag_active",1,1],"53":["res/prefabs/Loto/Loto_ItemNumSelected",2],"54":["res/popup/choi_ngay/round_1",1,1],"55":["res/prefabs/Loto/Loto_ItemChannel",2],"56":["res/game/round_date_location",1,1],"58":["res/game/bg",1,1],"59":["res/game/ket_qua_hang_ngay",1,1],"60":["res/game/bg_2",1,1],"61":["res/game/bg_1",1,1],"62":["res/prefabs/Loto/Loto_ItemChat",2],"66":["res/game/button_an_hien",1,1],"68":["res/game/mien_nam_inactive",1,1],"70":["res/game/so_da_chon_1",1,1],"71":["res/game/mien_trung_inactive",1,1],"72":["res/popup/history/round 2",1,1],"73":["res/game/bg_chat",1,1],"74":["res/common/iconCoinFish",1,1],"76":["res/prefabs/Loto/Loto_ItemNewBet",2],"78":["res/game/lich_su_cuoc",1,1],"79":["res/game/bg_top",1,1],"82":["res/popup/history/round_1",1,1],"83":["res/game/round_chat",1,1],"85":["res/game/bg_4",1,1],"86":["res/game/so_da_chon",1,1],"87":["res/popup/textTitleResult",1,1],"88":["res/game/icon_back",1,1],"89":["res/game/button_datcuoc",1,1],"90":["res/popup/choi_ngay/bg_2",1,1],"92":["res/prefabs/Loto/Loto_ItemNumber",2],"93":["res/game/bg_Gold",1,1]},"types":["cc.Texture2D","cc.SpriteFrame","cc.Prefab","cc.AudioClip"],"uuids":["01BK66uOJDq66Be+jUtgI3","0a58gR8EhJxLCpkNBbCqGy","10CSADhE9Og7xeAJtYkvi7","13tbiuqp5MY5XEn+kharwh","145GY3r+xIAqYuseSUz74V","1fJi2gqxtAmaS0zBOTjsfv","24tum1lhZDCYktFLsTY716","260fMyTtdGY7KWADLrXLgR","29w6WP/zJBt5VG2Z1QYqtd","30d1gaIepI2r0WNOxRYIac","30wSv6+UpDhIBulhCCmv8n","3fdE4bGIpGKaR0/e+agJcr","42RHWWpNJB5Zt0Pgr8POdD","42tX45xlRAIZdMz9zp/rdk","4ccnBOt0FNlI2HhanGfJfu","4cim1/5bRN+Ziylmst5koa","67j11aXmJERayuGUxtdv/w","6fEw1ZBxVBtKPjq9FwvG+V","78eSO/gs9CJ7aDDqlee+pI","791Bz4QG9BpoRivVTu7iIt","86lZ4aYp1M5ZM093Jzz3JS","87EV4mOsJFwY0Ht+YsQOgE","8fXacWC2tHVrfkgGqA9dWX","94vTJQw1pKKJGn1Xjyec6A","96wuIy0+tO7Lchgw9sWuSL","9dyHoSLApPdop3LAmE9AyA","9fzB5g2vlAFrXSSLNYgBFP","a2qnpYkvBOr544V+uqfknY","a3C+PCA0tBqbbSE0Vvls5t","a9bsIAOPxFzpbNIiuTYiBz","b1sqxNumRGdb4/R4Ggfqia","bfn6kNc/VNjKuvtIs5y1M4","c9UBp6J8pCYpTktfgzdzuH","cef2GzQIlKiqnsR+7QXrUy","d9ZkxI09hNVLAb8Ffd20Kh","e4UGtwILtLmaxWRN//NWoP","f1RnzVnNRNepu/quxNlINj","f6KknAJDBBgp3SdGtZ+U+A","0fdg+F4DpJQaMjaF8lIBl7","14M+IjiMRF9oBq6K9AlovG","18l/BfXoBAYaJuEZpXM5ex","19bXN3DoFPlJ0g69fMO7l5","1bvrztfX9PabUqFtmJQIuk","1bxiW0xZZKBb3qmkW/8+B6","2chTgKHBdKKYklKnHWDnFb","32pdhgZ7RP0ZAlEJAnOPN3","33ilGiMKhL9KTVD5eW7bvi","370uXE5YZEe5UtROoh8k3H","39XBOOxkBJgaBocJuCO+Mx","3dXzbZlRtD8axk2vJ5EF4R","44l5zuy1RBI69U7ExN0HZz","48xqdqzJlFeqBBcT6Rjg49","4a4g/DkM9H/Kz/xhX3JidJ","53MyFv/TlO4KMMeEvi5Hj9","58yW9R/CBNj4NsALi3p+4K","5d4XtjxgNDJ4VpZt4SigEb","5eiQpqS89MRZo6IAzrb8nm","60ao803qNKyLgTz6EKUZvV","64ISr15ldGK6UT3+s85cJM","65zQbcBMVKq7Rtufs1Tyz+","68S13ftK1AeoYIgQH/T88W","78myPR0O9EW7ctcmhtBVp3","7fEw3YAIdA1orMqt6Cm8u+","80aAJgnFhC8ZW850IJeXXI","8aF7w6Ep5FzaV4LqaPf9WB","9cgg1sEztG+LICseLnf+zr","9eCjI4WvtPW4mO1u2Apl1a","9ftOt/eGJNvLLPhE+KPMNn","a5HBVc1mFPbLmI8uWyfAGq","a9hN39Bk5NHIBIzJdE/M0/","b3g/HWAIJNtpetjlZ5+2Fw","b4MMZFIrFMEJaGrKSjAq9H","baaanypQJNpJerV0Xz2tpq","bau6IcvM5DXpDJw6dzA+Lc","beZQjmf2JAHZnof9oe07X0","c5KuF4b1ZONbvvbkaFAJMx","c69KhaNIdLYbrybNA8nMrW","calj5El+1MAoJ1zHScTKno","d0CpQn0w1O2ZK4AjDGLQY+","d6gJTlDKFPKKTeUfrBw9R+","d8wj8wrxhGS6IikcIfnr6k","daHbtWGoZI+qsHt8rUE0Kq","dfH6dcZNpBbYtgU2mmd5o/","e16tooBwFBO6GMyeP30/NM","e3kQScUVtMN4ZWY40mcAQd","e7IFTKX2hL0LcEyZVt7z2n","eaHOT8V9ZLZanqj9dWWHpl","ea6e0MP3FDEpwI5lcZy4Gz","ecQ3pWFrhKaqePzjA9KQ6O","f31hcLoXVOIpW+3zX55u/J","f6yyCn2JxL3pidvCng5NA9","f7R2iHeH9L0KeD060gYtIc","fdC1uS0g9J+4xUoL3YdG2w","fdW/KcLw9NKrM0P59ndT6L","15hw04s/xJlZd7o1LOcInD","15mHAGryJGbYp1N79dTexW","2aRU6cm7VNxKvnYihB+5dT","55c60BdfNFT4FN7GxMcVY7","5dKN47sElHmpcj+OVuw8kS","6921figkJBOZnCF9AUuUEI","7a/QZLET9IDreTiBfRn2PD","7dZVDJ6lVM3q9RwNr1sk6t","7fmkeDiB9PS7dpIqdxftqn","83dX5+AxBDXrQbDfqQ7pID","a2MjXRFdtLlYQ5ouAFv/+R","a6re5y3AFNMLzUJVEw5ktx","aaD6uAnixAMpafzr9oTfsu","c4KumOXt1A05Y2CW47rqaW","c5GR5x0vRH8amsssxYnZLB","d19RJMe1xLN7CEgOfqwNoM","d7/s9PuoNPwaI7VBP40xI7","deM9EOvlVBy7Ds6/X5kj9F","e9fRxQdyRNdohHuaF7fNc/","ecpdLyjvZBwrvm+cedCcQy","fcXT5X4edMYKqmH8hZAmmr"],"scenes":{"db://assets/Loto/Loto.fire":81},"redirect":[95,0,96,0,97,0,99,0,100,1,102,0,104,0,105,0,113,1],"deps":["Lobby","internal"],"packs":{"02342a581":[46,72],"03a0c59f5":[54,55],"05bb28ed9":[1,2,3,4,43,5,6,7,8,9,10,11,12,13,14,15,57,16,17,18,19,63,20,21,64,22,23,24,65,25,67,26,27,28,29,69,30,31,75,32,77,33,80,34,84,35,36,37,91],"0ac7a8709":[49,70,92],"0adc22085":[53,86],"0f17e663b":[0,38,39,94,40,41,42,44,45,47,48,50,51,52,98,56,58,59,60,61,101,62,103,66,68,106,71,73,74,107,108,76,78,109,79,110,81,111,82,83,85,112,87,88,89,90,114,93]},"name":"Loto","importBase":"import","nativeBase":"native","debug":false,"isZip":false,"encrypted":false,"versions":{"import":["02342a581","f3753","03a0c59f5","a4ae5","05bb28ed9","03601","0ac7a8709","5d1b3","0adc22085","31582","0f17e663b","e5c1e"],"native":[0,"e1036",1,"12d2f",2,"3b577",3,"c5b1e",4,"6732a",43,"976b2",5,"584a0",6,"072b7",7,"2c5d0",8,"ed1dd",9,"f76bd",10,"463ef",11,"4e2bb",12,"f93d8",13,"d15e9",14,"f6d31",15,"d1d0f",57,"119c1",16,"b178f",17,"0775a",18,"1aa7b",19,"c912c",63,"375de",20,"33a08",21,"8b829",64,"ee67c",22,"147b4",23,"3763d",24,"77edc",65,"760d7",25,"af0a7",67,"8a3ac",26,"78007",27,"32977",28,"2fbb3",29,"da089",69,"2b3e6",30,"6f676",31,"42be5",75,"6f45f",32,"af235",77,"21fe7",33,"4b75c",80,"32560",34,"e76eb",84,"2f5f5",35,"1bc76",36,"2b748",37,"ef80f",91,"de72d"]}}